{
  "closed": 3,
  "data": [
    {
      "id": "PR_kwDOK9tITM5qVcby",
      "title": "fix issue: Update README.md",
      "url": "https://github.com/Nandini80/CityPlus/pull/22",
      "state": "MERGED",
      "mergedBy": {
        "avatarUrl": "https://avatars.githubusercontent.com/u/121488571?u=f1bcbe972fa9605d512f29693bdaf72ac966d72b&v=4",
        "url": "https://github.com/Nandini80",
        "login": "Nandini80"
      },
      "createdAt": "2024-03-21T09:30:18Z",
      "number": 22,
      "changedFiles": 1,
      "additions": 69,
      "deletions": 27,
      "baseRepository": {
        "name": "CityPlus",
        "url": "https://github.com/Nandini80/CityPlus",
        "owner": {
          "avatarUrl": "https://avatars.githubusercontent.com/u/121488571?u=f1bcbe972fa9605d512f29693bdaf72ac966d72b&v=4",
          "login": "Nandini80",
          "url": "https://github.com/Nandini80"
        }
      }
    },
    {
      "id": "PR_kwDOK6bXcs5p43bP",
      "title": "Fix issue #10 : Forgot Password Page",
      "url": "https://github.com/Nandini80/Pill-Share/pull/29",
      "state": "MERGED",
      "mergedBy": {
        "avatarUrl": "https://avatars.githubusercontent.com/u/121488571?u=f1bcbe972fa9605d512f29693bdaf72ac966d72b&v=4",
        "url": "https://github.com/Nandini80",
        "login": "Nandini80"
      },
      "createdAt": "2024-03-18T04:36:30Z",
      "number": 29,
      "changedFiles": 1,
      "additions": 1,
      "deletions": 1,
      "baseRepository": {
        "name": "Pill-Share",
        "url": "https://github.com/Nandini80/Pill-Share",
        "owner": {
          "avatarUrl": "https://avatars.githubusercontent.com/u/121488571?u=f1bcbe972fa9605d512f29693bdaf72ac966d72b&v=4",
          "login": "Nandini80",
          "url": "https://github.com/Nandini80"
        }
      }
    },
    {
      "id": "PR_kwDOIhMtrM5p3BB2",
      "title": "fix: Align image on about page",
      "url": "https://github.com/Kritika30032002/Top_Secrets/pull/172",
      "state": "MERGED",
      "mergedBy": {
        "avatarUrl": "https://avatars.githubusercontent.com/u/83400697?u=9d7e6220f820a79658009de8fbd6559086df779a&v=4",
        "url": "https://github.com/Kritika30032002",
        "login": "Kritika30032002"
      },
      "createdAt": "2024-03-17T12:35:36Z",
      "number": 172,
      "changedFiles": 3,
      "additions": 1380,
      "deletions": 1207,
      "baseRepository": {
        "name": "Top_Secrets",
        "url": "https://github.com/Kritika30032002/Top_Secrets",
        "owner": {
          "avatarUrl": "https://avatars.githubusercontent.com/u/83400697?u=9d7e6220f820a79658009de8fbd6559086df779a&v=4",
          "login": "Kritika30032002",
          "url": "https://github.com/Kritika30032002"
        }
      }
    },
    {
      "id": "PR_kwDOJ_kXmc5p23gE",
      "title": "fix issue 6: Updated README.md",
      "url": "https://github.com/BTANISHA11/medcare/pull/9",
      "state": "MERGED",
      "mergedBy": {
        "avatarUrl": "https://avatars.githubusercontent.com/u/110708865?u=46669986d874ebff0e4af589e9372966faf94662&v=4",
        "url": "https://github.com/BTANISHA11",
        "login": "BTANISHA11"
      },
      "createdAt": "2024-03-17T10:47:34Z",
      "number": 9,
      "changedFiles": 1,
      "additions": 74,
      "deletions": 15,
      "baseRepository": {
        "name": "medcare",
        "url": "https://github.com/BTANISHA11/medcare",
        "owner": {
          "avatarUrl": "https://avatars.githubusercontent.com/u/110708865?u=46669986d874ebff0e4af589e9372966faf94662&v=4",
          "login": "BTANISHA11",
          "url": "https://github.com/BTANISHA11"
        }
      }
    },
    {
      "id": "PR_kwDOK6bXcs5p2qXh",
      "title": "Fix issue 6 : Updated README.md",
      "url": "https://github.com/Nandini80/Pill-Share/pull/28",
      "state": "MERGED",
      "mergedBy": {
        "avatarUrl": "https://avatars.githubusercontent.com/u/121488571?u=f1bcbe972fa9605d512f29693bdaf72ac966d72b&v=4",
        "url": "https://github.com/Nandini80",
        "login": "Nandini80"
      },
      "createdAt": "2024-03-17T07:55:52Z",
      "number": 28,
      "changedFiles": 3,
      "additions": 88,
      "deletions": 10,
      "baseRepository": {
        "name": "Pill-Share",
        "url": "https://github.com/Nandini80/Pill-Share",
        "owner": {
          "avatarUrl": "https://avatars.githubusercontent.com/u/121488571?u=f1bcbe972fa9605d512f29693bdaf72ac966d72b&v=4",
          "login": "Nandini80",
          "url": "https://github.com/Nandini80"
        }
      }
    },
    {
      "id": "PR_kwDOIhMtrM5p1uQ1",
      "title": "fix: Sign Up with Facebook",
      "url": "https://github.com/Kritika30032002/Top_Secrets/pull/171",
      "state": "MERGED",
      "mergedBy": {
        "avatarUrl": "https://avatars.githubusercontent.com/u/83400697?u=9d7e6220f820a79658009de8fbd6559086df779a&v=4",
        "url": "https://github.com/Kritika30032002",
        "login": "Kritika30032002"
      },
      "createdAt": "2024-03-16T21:15:44Z",
      "number": 171,
      "changedFiles": 2,
      "additions": 37,
      "deletions": 1,
      "baseRepository": {
        "name": "Top_Secrets",
        "url": "https://github.com/Kritika30032002/Top_Secrets",
        "owner": {
          "avatarUrl": "https://avatars.githubusercontent.com/u/83400697?u=9d7e6220f820a79658009de8fbd6559086df779a&v=4",
          "login": "Kritika30032002",
          "url": "https://github.com/Kritika30032002"
        }
      }
    },
    {
      "id": "PR_kwDOIEGbhs5puFel",
      "title": "Fix issue 48 : Fixed Favorite Icon and Home Icon",
      "url": "https://github.com/lcrojano/Giphy_Explorer/pull/49",
      "state": "MERGED",
      "mergedBy": {
        "avatarUrl": "https://avatars.githubusercontent.com/u/5177737?u=82116f5ac719b0c3d0840f34c9ff724963b88c57&v=4",
        "url": "https://github.com/lcrojano",
        "login": "lcrojano"
      },
      "createdAt": "2024-03-15T08:59:59Z",
      "number": 49,
      "changedFiles": 7,
      "additions": 551,
      "deletions": 428,
      "baseRepository": {
        "name": "Giphy_Explorer",
        "url": "https://github.com/lcrojano/Giphy_Explorer",
        "owner": {
          "avatarUrl": "https://avatars.githubusercontent.com/u/5177737?u=82116f5ac719b0c3d0840f34c9ff724963b88c57&v=4",
          "login": "lcrojano",
          "url": "https://github.com/lcrojano"
        }
      }
    },
    {
      "id": "PR_kwDOJX56t85pqQsA",
      "title": "Add profile : Adarsh",
      "url": "https://github.com/shyamtawli/devFind/pull/909",
      "state": "MERGED",
      "mergedBy": {
        "avatarUrl": "https://avatars.githubusercontent.com/u/104145978?u=bf46b4f51a4d6d73c66ca7b6f4e9dc0e9fd357e5&v=4",
        "url": "https://github.com/shyamtawli",
        "login": "shyamtawli"
      },
      "createdAt": "2024-03-14T17:30:29Z",
      "number": 909,
      "changedFiles": 2,
      "additions": 14,
      "deletions": 1,
      "baseRepository": {
        "name": "devFind",
        "url": "https://github.com/shyamtawli/devFind",
        "owner": {
          "avatarUrl": "https://avatars.githubusercontent.com/u/104145978?u=bf46b4f51a4d6d73c66ca7b6f4e9dc0e9fd357e5&v=4",
          "login": "shyamtawli",
          "url": "https://github.com/shyamtawli"
        }
      }
    },
    {
      "id": "PR_kwDOK6bXcs5pnwWF",
      "title": "Fix issue #9 : Make Certain Options Mandatory in Profile Form",
      "url": "https://github.com/Nandini80/Pill-Share/pull/16",
      "state": "MERGED",
      "mergedBy": {
        "avatarUrl": "https://avatars.githubusercontent.com/u/121488571?u=f1bcbe972fa9605d512f29693bdaf72ac966d72b&v=4",
        "url": "https://github.com/Nandini80",
        "login": "Nandini80"
      },
      "createdAt": "2024-03-14T12:09:19Z",
      "number": 16,
      "changedFiles": 4,
      "additions": 30,
      "deletions": 17,
      "baseRepository": {
        "name": "Pill-Share",
        "url": "https://github.com/Nandini80/Pill-Share",
        "owner": {
          "avatarUrl": "https://avatars.githubusercontent.com/u/121488571?u=f1bcbe972fa9605d512f29693bdaf72ac966d72b&v=4",
          "login": "Nandini80",
          "url": "https://github.com/Nandini80"
        }
      }
    },
    {
      "id": "PR_kwDOKBFKvs5bTMtX",
      "title": "profile Added - jinx-vi-0",
      "url": "https://github.com/hellofaizan/xprofile/pull/95",
      "state": "MERGED",
      "mergedBy": {
        "avatarUrl": "https://avatars.githubusercontent.com/u/84437051?u=fb70e3c4f3d8bdf398bbcc0c1902f12cb31ff778&v=4",
        "url": "https://github.com/hellofaizan",
        "login": "hellofaizan"
      },
      "createdAt": "2023-09-27T06:35:29Z",
      "number": 95,
      "changedFiles": 1,
      "additions": 9,
      "deletions": 1,
      "baseRepository": {
        "name": "xprofile",
        "url": "https://github.com/hellofaizan/xprofile",
        "owner": {
          "avatarUrl": "https://avatars.githubusercontent.com/u/84437051?u=fb70e3c4f3d8bdf398bbcc0c1902f12cb31ff778&v=4",
          "login": "hellofaizan",
          "url": "https://github.com/hellofaizan"
        }
      }
    },
    {
      "id": "PR_kwDOKVIvO85arP7Q",
      "title": "Updated details.txt",
      "url": "https://github.com/jinx-vi-0/github_sheet/pull/1",
      "state": "MERGED",
      "mergedBy": {
        "avatarUrl": "https://avatars.githubusercontent.com/u/120160355?u=20bbcb03633cbf7d28cb9af71c01c65783fa7cc8&v=4",
        "url": "https://github.com/jinx-vi-0",
        "login": "jinx-vi-0"
      },
      "createdAt": "2023-09-19T13:06:13Z",
      "number": 1,
      "changedFiles": 1,
      "additions": 3,
      "deletions": 0,
      "baseRepository": {
        "name": "github_sheet",
        "url": "https://github.com/jinx-vi-0/github_sheet",
        "owner": {
          "avatarUrl": "https://avatars.githubusercontent.com/u/120160355?u=20bbcb03633cbf7d28cb9af71c01c65783fa7cc8&v=4",
          "login": "jinx-vi-0",
          "url": "https://github.com/jinx-vi-0"
        }
      }
    },
    {
      "id": "PR_kwDOKNafoM5agTxx",
      "title": "jinx-vi-0",
      "url": "https://github.com/scaleracademy/scaler-open-source-september-challenge/pull/1095",
      "state": "OPEN",
      "mergedBy": null,
      "createdAt": "2023-09-17T07:37:09Z",
      "number": 1095,
      "changedFiles": 3,
      "additions": 30,
      "deletions": 1,
      "baseRepository": {
        "name": "scaler-open-source-september-challenge",
        "url": "https://github.com/scaleracademy/scaler-open-source-september-challenge",
        "owner": {
          "avatarUrl": "https://avatars.githubusercontent.com/u/57796181?v=4",
          "login": "scaleracademy",
          "url": "https://github.com/scaleracademy"
        }
      }
    },
    {
      "id": "PR_kwDOKNafoM5ZkeqX",
      "title": "Added jinx-vi-0.md",
      "url": "https://github.com/scaleracademy/scaler-open-source-september-challenge/pull/629",
      "state": "CLOSED",
      "mergedBy": null,
      "createdAt": "2023-09-05T12:34:08Z",
      "number": 629,
      "changedFiles": 0,
      "additions": 0,
      "deletions": 0,
      "baseRepository": {
        "name": "scaler-open-source-september-challenge",
        "url": "https://github.com/scaleracademy/scaler-open-source-september-challenge",
        "owner": {
          "avatarUrl": "https://avatars.githubusercontent.com/u/57796181?v=4",
          "login": "scaleracademy",
          "url": "https://github.com/scaleracademy"
        }
      }
    },
    {
      "id": "PR_kwDOEf72xc5ZiBnA",
      "title": "Added Profile Card",
      "url": "https://github.com/thinkswell/javascript-mini-projects/pull/565",
      "state": "MERGED",
      "mergedBy": {
        "avatarUrl": "https://avatars.githubusercontent.com/u/45295239?u=fed8ce93919b447bd92b60daf1f037379ed55f64&v=4",
        "url": "https://github.com/thinkswell",
        "login": "thinkswell"
      },
      "createdAt": "2023-09-05T04:29:19Z",
      "number": 565,
      "changedFiles": 4,
      "additions": 155,
      "deletions": 0,
      "baseRepository": {
        "name": "javascript-mini-projects",
        "url": "https://github.com/thinkswell/javascript-mini-projects",
        "owner": {
          "avatarUrl": "https://avatars.githubusercontent.com/u/45295239?u=fed8ce93919b447bd92b60daf1f037379ed55f64&v=4",
          "login": "thinkswell",
          "url": "https://github.com/thinkswell"
        }
      }
    },
    {
      "id": "PR_kwDODUr5jM5Zh7S0",
      "title": "Refine Scroll to Top appearance",
      "url": "https://github.com/alisolanki/Portfolio/pull/8",
      "state": "CLOSED",
      "mergedBy": null,
      "createdAt": "2023-09-05T03:45:44Z",
      "number": 8,
      "changedFiles": 1,
      "additions": 5,
      "deletions": 2,
      "baseRepository": {
        "name": "Portfolio",
        "url": "https://github.com/alisolanki/Portfolio",
        "owner": {
          "avatarUrl": "https://avatars.githubusercontent.com/u/55312000?u=04736d73007ebe9da6d299efe4bd01018e3573c6&v=4",
          "login": "alisolanki",
          "url": "https://github.com/alisolanki"
        }
      }
    },
    {
      "id": "PR_kwDOEDBOdM5ZeSaN",
      "title": "Added response to navbar",
      "url": "https://github.com/arvind37/Basic-Website-using-HTML-CSS/pull/12",
      "state": "CLOSED",
      "mergedBy": null,
      "createdAt": "2023-09-04T11:20:35Z",
      "number": 12,
      "changedFiles": 1,
      "additions": 9,
      "deletions": 8,
      "baseRepository": {
        "name": "Basic-Website-using-HTML-CSS",
        "url": "https://github.com/arvind37/Basic-Website-using-HTML-CSS",
        "owner": {
          "avatarUrl": "https://avatars.githubusercontent.com/u/55478740?v=4",
          "login": "arvind37",
          "url": "https://github.com/arvind37"
        }
      }
    },
    {
      "id": "PR_kwDOBobu3s5Zd51d",
      "title": "new student : Adarsh added",
      "url": "https://github.com/rishz/make-a-pull-request/pull/1577",
      "state": "OPEN",
      "mergedBy": null,
      "createdAt": "2023-09-04T10:15:17Z",
      "number": 1577,
      "changedFiles": 1,
      "additions": 3,
      "deletions": 0,
      "baseRepository": {
        "name": "make-a-pull-request",
        "url": "https://github.com/rishz/make-a-pull-request",
        "owner": {
          "avatarUrl": "https://avatars.githubusercontent.com/u/20211622?u=bb59d4210d2ccc159075db1ceedd8b31d523e4c8&v=4",
          "login": "rishz",
          "url": "https://github.com/rishz"
        }
      }
    }
  ],
  "merged": 12,
  "open": 2,
  "totalCount": 17
}
